otto_api42/__init__.py
otto_api42/config.sample.yml
otto_api42/intra.py
otto_api42/typings.py
otto_api42-0.1.5.dist-info/METADATA
otto_api42-0.1.5.dist-info/WHEEL
otto_api42-0.1.5.dist-info/licenses/LICENSE
otto_api42-0.1.5.dist-info/RECORD
