Metadata-Version: 2.4
Name: otto_api42
Version: 0.1.5
Summary: The 42 Intranet API as a powerful and Py-ful package
Project-URL: Homepage, https://github.com/otto-mata/api42
Project-URL: Issues, https://github.com/otto-mata/api42/issues
Author-email: ottomata <ottomata@proton.me>
License-Expression: MIT
License-File: LICENSE
Classifier: Operating System :: OS Independent
Classifier: Programming Language :: Python :: 3
Requires-Python: >=3.10
